llama_index/graph_stores/memgraph/__init__.py
llama_index/graph_stores/memgraph/kg_base.py
llama_index/graph_stores/memgraph/property_graph.py
llama_index_graph_stores_memgraph-0.4.1.dist-info/METADATA
llama_index_graph_stores_memgraph-0.4.1.dist-info/WHEEL
llama_index_graph_stores_memgraph-0.4.1.dist-info/licenses/LICENSE
llama_index_graph_stores_memgraph-0.4.1.dist-info/RECORD
